tvtimewrapper/__init__.py
tvtimewrapper/episode.py
tvtimewrapper/exceptions.py
tvtimewrapper/show.py
tvtimewrapper/user.py
tvtimewrapper-0.0.3.dist-info/LICENSE
tvtimewrapper-0.0.3.dist-info/METADATA
tvtimewrapper-0.0.3.dist-info/WHEEL
tvtimewrapper-0.0.3.dist-info/top_level.txt
tvtimewrapper-0.0.3.dist-info/RECORD
